[
  {
    "text": "03장\n클라우드 컴퓨팅 서비스에 저장된 국가핵심기술 관련 정보에 대한 \n외국기업 등의 접근권한 부여‧열람‧사용 등을 허용하는 경우\n기본원칙 ····································································································· 35 \n보안관리 ····································································································· 36 \n[별 첨1]\n[별 첨2]\n국내·외 클라우드 컴퓨팅 서비스 관련 법·제도 현황\n클라우드 컴퓨팅 서비스 환경에서의 국가핵심기술 보호 실태조사 체크리스트\n",
    "metadata": {
      "page": 4,
      "source": "국가핵심기술+클라우드+컴퓨팅+서비스+이용을+위한+보안관리+안내서(배포용).pdf",
      "chunk_index": 0,
      "chunk_method": "semantic_local"
    }
  }
]