[
  {
    "text": "국가핵심기술의 클라우드 \n컴퓨팅 서비스 활용을 위한 보호조치 안내서\n6\n  [1단계] 국가핵심기술 보유기관 및 클라우드 컴퓨팅 서비스 사업자 개별 \n보안관리 항목 도출\n   ☞ 국가핵심기술 보유기관의 경우, 국가·공공기관의 클라우드 컴퓨팅 도입 시, \n보안수준을 향상시킬 수 있는 보안성 확인 기준인 「국가 클라우드 \n컴퓨팅 보안 가이드라인」(국정원)을 참고하여 이용자 문항 도출\n   ☞ 클라우드 컴퓨팅 서비스 사업자의 경우, 제공하는 서비스에 대해 「클라우드\n컴퓨팅 발전 및 이용자 보호에 관한 법률」 제23조의2에 따라 정보보호 \n수준의 향상 및 보장을 위한 「클라우드컴퓨팅서비스 보안인증제도 안내서」\n(과기부)를 참고하여 제공자 문항 도출\n  이용자 예시\n국가 클라우드 컴퓨팅 보안 \n가이드라인\n도출 항목\n‣이용기관은 민간 사업자가 클라우드 컴퓨팅 \n서비스망을 대상으로 자체적으로 수행한 \n운용관리에 대한 보안 취약성 개선 결과를 \n주기적으로 보고받아야 한다. ‣이용기관은 민간 사업자가 클라우드 컴퓨팅 \n서비스망에 대하여 자체적으로 실시한 \n모의훈련 및 취약점 점검 결과를 주기적\n으로 확인하여야 한다. ⇨\n‣▲이용자는 제공자가 자체 또는 외부 전문\n기관으로부터 수행한 클라우드 컴퓨팅 서비스 \n운용관리 전반에 대한 보안 취약점 개선 \n결과를 확인하여야 하며, ▲제공자는 운용관리 \n전반에 대한 보안 취약점 점검을 정기적으로 \n이행하고, 점검 및 개선 결과를 이용자에게 \n제공하여야 한다. ‣이용기관은 중요 업무자료에 대한 암호화 \n수준 등에 대한 보안 요구사항을 도출하여 \n계약 시 반영하여야 하며, 중요 업무자료에 \n대한 생성‧보관‧처리‧수신하기 위한 정책적‧\n기술적 방안을 민간 사업자로부터 제공\n받아야 한다. ‣국가핵심기술 관련 정보에 대한 ▲암호화 수준에 \n대한 보안 요구사항을 도출하여 계약 시 \n반영하여야 하며, ▲생성된 국가핵심기술 관련 \n정보에 대한 생성‧보관‧처리‧수신하기 위한 \n기술적 방안 등을 제공자에게 제공받아야 한다. ‣이용기관은 침해사고 발생 시 민간 사업자\n로부터 발생내용, 원인, 조치현황 등을 \n신속하게 파악하고 「국가 정보보안 기본\n지침」에 명시된 사고 대응 절차를 수행\n하여야 한다. ‣클라우드 컴퓨팅 서비스와 관련하여 ▲침해\n사고 발생 시, 제공자로부터 발생내용, \n원인, 조치현황 등을 신속하게 파악하고, \n▲사고대응 절차를 수행하여야 한다.",
    "metadata": {
      "page": 12,
      "source": "국가핵심기술+클라우드+컴퓨팅+서비스+이용을+위한+보안관리+안내서(배포용).pdf",
      "chunk_index": 0,
      "chunk_method": "semantic_local"
    }
  },
  {
    "text": "",
    "metadata": {
      "page": 12,
      "source": "국가핵심기술+클라우드+컴퓨팅+서비스+이용을+위한+보안관리+안내서(배포용).pdf",
      "chunk_index": 1,
      "chunk_method": "semantic_local"
    }
  }
]