[
  {
    "text": "26\n정보의 제공\n1-2-2. 개발사업자\n이용사업자\n목표\n개발사업자는 이용사업자 및 이용자에게\n이용사업자는 이용자에게 인공지능 위험과 관련된 충분한 \n, \n정보를 제공하기 위해 노력해야 함. 설명\n개발사업자는 고영향 인공지능을 개발하거나 이를 고도화하여 제공하는 책임 주체로서인공지능의 주요 \n, \n기능과 작동 원리사용 데이터의 특성자동화된 결정 방식과 한계 등에 대한 정보를 이용사업자에게 \n, \n, \n충분히 제공하기 위해 노력해야 함. 인공지능 사용 시 발생할 수 있는 윤리적 문제 및 예기치 않은 오작동 가능성과 그에 대한 대응 절차에 \n- \n대해서 가능한한 충분한 정보를 제공할 필요가 있으며사용자 매뉴얼\n동영상 자료 등 다양한 \n, \n, FAQ, \n형식의 자료를 마련하여 제공하고이를 주기적으로 최신화하기 위해 노력해야 함\n, \n. 또한개선 이력이나 보안 업데이트 등의 중요 정보를 지속적으로 공유하여 이용자가 인공지능을 안전하게 \n- \n, \n사용할 수 있도록 지원해야 함. 이용사업자는 개발사업자로부터 제공받은 인공지능을 자사의 제품서비스에 활용하는 주체로서\n해당 \n·\n, \n인공지능이 이용자에게 미치는 영향에 대한 정보를 이용자에게 제공하기 위해 노력해야 함. 우선 제품서비스 내 인공지능 활용 사실을 고지하고인공지능이 수행하는 역할자동화 여부인간의 \n- \n·\n, \n, \n, \n개입 범위 및 결정이 이용자의 권리에 미치는 영향을 가능한 충분히 설명해야 함. 또한 이용자가 자신의 정보 처리 방식이의 제기 절차문제 발생 시 신고나 상담 방법에 대해 알 수 \n- \n, \n, \n있도록 이용약관공지사항홈페이지사용 설명서 등을 통해 정보를 투명하게 제공할 수 있음\n, \n, \n, \n. 참고\n\n신뢰할 수 있는 인공지능 개발안내서\n韓 \n요구사항 \n서비스 제공 범위 및 상호작용 대상에 대한 설명 제공\n- \n15. 요구사항 \n인공지능 서비스의 올바른 사용을 유도하기 위한 설명을 제공하는가\n- \n15-1.",
    "metadata": {
      "page": 27,
      "source": "4._260122_고영향_인공지능_사업자_책무_가이드라인-1.pdf",
      "chunk_index": 0,
      "chunk_method": "semantic_local"
    }
  },
  {
    "text": "? \nNIST AI RMF\n美 \n-\n인공지능 위험 관리 및 효과성을 위해 인공지능 시스템에 적용되는 법률정책규정 등의 \nGOVERN 2.2: \n, \n, \n정보 제공\nEU AI ACT\n- 제조제항제호고위험 인공지능 시스템 운영 중 위험 감소를 위해 적절한 정보 제공\n9\n5\nc\n: \n- 제\n조제항고위험 인공지능 시스템의 안전한 사용을 위해 이용자에게 사용 지침 제공\n13\n2\n: \n사업자 구분\n자가점검\n인공지능 위험 정보를 충분히 제공하고 있는가? 정보 제공에 사용되는 자료의 형식 및 방법은 적절한가? 개발 이용 \n개발 이용 \n사례\n인공지능 정보 제공 방법\n인공지능에 대해 충분한 정보를 제공하기 위한 방법은 아래와 같이 다양한 형식으로 제공될 수 있음. 정보제공 대상\n예시\n이용자\n튜토리얼 영상\n경고 문구사용 가이드\n, \n, \n이용사업자기업고객\n(\n)\n워크숍\n문서\n활용 가이드북책임 사용 가이드\n, API \n, \n, \n개발사업자내부직원\n(\n)\n문제 발생 대응 매뉴얼\n",
    "metadata": {
      "page": 27,
      "source": "4._260122_고영향_인공지능_사업자_책무_가이드라인-1.pdf",
      "chunk_index": 1,
      "chunk_method": "semantic_local"
    }
  }
]