[
  {
    "text": "이 가이드라인(안)은 전문가, 실무자, 그리고 다양한 이해관계자의 의견을 모아, \n해외 동향과 인공지능 기술의 발전, 서비스 형태 등을 종합적으로 반영해 작성 중인 자료입니다. 따라서 여기에 담긴 내용은 앞으로 공개될 최종본과는 달라질 수 있습니다.",
    "metadata": {
      "page": 2,
      "source": "2._260122_인공지능_안전성_확보_가이드라인.pdf",
      "chunk_index": 0,
      "chunk_method": "semantic_local"
    }
  },
  {
    "text": "",
    "metadata": {
      "page": 2,
      "source": "2._260122_인공지능_안전성_확보_가이드라인.pdf",
      "chunk_index": 1,
      "chunk_method": "semantic_local"
    }
  }
]